MzhFunc-0.1.5.data/data/requirements.txt
db/MzhFunc.py
db/__init__.py
MzhFunc-0.1.5.dist-info/METADATA
MzhFunc-0.1.5.dist-info/WHEEL
MzhFunc-0.1.5.dist-info/top_level.txt
MzhFunc-0.1.5.dist-info/RECORD
