Metadata-Version: 2.1
Name: MzhFunc
Version: 0.1.5
Summary: Python helper tools
Home-page: https://pypi.org/project/MzhFunc/
Author: Author's name
Author-email: 191891173@qq.com
Classifier: Programming Language :: Python :: 3
Classifier: License :: OSI Approved :: MIT License
Classifier: Operating System :: OS Independent
